[{"StartColor":"#FFFDEB71","StopColor":"#FFF8D800"},{"StartColor":"#FFABDCFF","StopColor":"#FF0396FF"},{"StartColor":"#FFFEB692","StopColor":"#FFEA5455"},{"StartColor":"#FFCE9FFC","StopColor":"#FF7367F0"},{"StartColor":"#FF90F7EC","StopColor":"#FF32CCBC"},{"StartColor":"#FFFFF6B7","StopColor":"#FFF6416C"},{"StartColor":"#FF81FBB8","StopColor":"#FF28C76F"},{"StartColor":"#FFE2B0FF","StopColor":"#FF9F44D3"},{"StartColor":"#FFF97794","StopColor":"#FF623AA2"},{"StartColor":"#FFFCCF31","StopColor":"#FFF55555"},{"StartColor":"#FFF761A1","StopColor":"#FF8C1BAB"},{"StartColor":"#FF43CBFF","StopColor":"#FF9708CC"},{"StartColor":"#FF5EFCE8","StopColor":"#FF736EFE"},{"StartColor":"#FFFAD7A1","StopColor":"#FFE96D71"},{"StartColor":"#FFFFD26F","StopColor":"#FF3677FF"},{"StartColor":"#FFA0FE65","StopColor":"#FFFA016D"},{"StartColor":"#FFFFDB01","StopColor":"#FF0E197D"},{"StartColor":"#FFFEC163","StopColor":"#FFDE4313"},{"StartColor":"#FF92FFC0","StopColor":"#FF002661"},{"StartColor":"#FFEEAD92","StopColor":"#FF6018DC"},{"StartColor":"#FFF6CEEC","StopColor":"#FFD939CD"},{"StartColor":"#FF52E5E7","StopColor":"#FF130CB7"},{"StartColor":"#FFF1CA74","StopColor":"#FFA64DB6"},{"StartColor":"#FFE8D07A","StopColor":"#FF5312D6"},{"StartColor":"#FFEECE13","StopColor":"#FFB210FF"},{"StartColor":"#FF79F1A4","StopColor":"#FF0E5CAD"},{"StartColor":"#FFFDD819","StopColor":"#FFE80505"},{"StartColor":"#FFFFF3B0","StopColor":"#FFCA26FF"},{"StartColor":"#FFFFF5C3","StopColor":"#FF9452A5"},{"StartColor":"#FFF05F57","StopColor":"#FF360940"},{"StartColor":"#FF2AFADF","StopColor":"#FF4C83FF"},{"StartColor":"#FFFFF886","StopColor":"#FFF072B6"},{"StartColor":"#FF97ABFF","StopColor":"#FF123597"},{"StartColor":"#FFF5CBFF","StopColor":"#FFC346C2"},{"StartColor":"#FFFFF720","StopColor":"#FF3CD500"},{"StartColor":"#FFFF6FD8","StopColor":"#FF3813C2"},{"StartColor":"#FFEE9AE5","StopColor":"#FF5961F9"},{"StartColor":"#FFFFD3A5","StopColor":"#FFFD6585"},{"StartColor":"#FFC2FFD8","StopColor":"#FF465EFB"},{"StartColor":"#FFFD6585","StopColor":"#FF0D25B9"},{"StartColor":"#FFFD6E6A","StopColor":"#FFFFC600"},{"StartColor":"#FF65FDF0","StopColor":"#FF1D6FA3"},{"StartColor":"#FF6B73FF","StopColor":"#FF000DFF"},{"StartColor":"#FFFF7AF5","StopColor":"#FF513162"},{"StartColor":"#FFF0FF00","StopColor":"#FF58CFFB"},{"StartColor":"#FFFFE985","StopColor":"#FFFA742B"},{"StartColor":"#FFFFA6B7","StopColor":"#FF1E2AD2"},{"StartColor":"#FFFFAA85","StopColor":"#FFB3315F"},{"StartColor":"#FF72EDF2","StopColor":"#FF5151E5"},{"StartColor":"#FFFF9D6C","StopColor":"#FFBB4E75"},{"StartColor":"#FFF6D242","StopColor":"#FFFF52E5"},{"StartColor":"#FF69FF97","StopColor":"#FF00E4FF"},{"StartColor":"#FF3B2667","StopColor":"#FFBC78EC"},{"StartColor":"#FF70F570","StopColor":"#FF49C628"},{"StartColor":"#FF3C8CE7","StopColor":"#FF00EAFF"},{"StartColor":"#FFFAB2FF","StopColor":"#FF1904E5"},{"StartColor":"#FF81FFEF","StopColor":"#FFF067B4"},{"StartColor":"#FFFFA8A8","StopColor":"#FFFCFF00"},{"StartColor":"#FFFFCF71","StopColor":"#FF2376DD"},{"StartColor":"#FFFF96F9","StopColor":"#FFC32BAC"}]